django_medusa_unstoppable-0.3.1.dist-info/WHEEL
django_medusa_unstoppable-0.3.1.dist-info/DESCRIPTION.rst
django_medusa_unstoppable-0.3.1.dist-info/metadata.json
django_medusa_unstoppable-0.3.1.dist-info/top_level.txt
django_medusa_unstoppable-0.3.1.dist-info/RECORD
django_medusa_unstoppable-0.3.1.dist-info/METADATA
django_medusa/utils.py
django_medusa/__init__.py
django_medusa/renderers/s3.py
django_medusa/renderers/appengine.py
django_medusa/renderers/base.py
django_medusa/renderers/disk.py
django_medusa/renderers/__init__.py
django_medusa/management/__init__.py
django_medusa/management/commands/__init__.py
django_medusa/management/commands/staticsitegen.py
