Metadata-Version: 2.0
Name: django-medusa-unstoppable
Version: 0.3.1
Summary: A Django static website generator. Fork of django-medusa
Home-page: https://github.com/GeoTob/django-medusa-unstoppable
Author: Tobias Schulmann
Author-email: tobiasschulmann@catalyst.net.nz
License: MIT
Download-URL: https://github.com/GeoTob/django-medusa-unstoppable/releases/tag/0.3.1
Keywords: django static staticwebsite staticgenerator publishing
Platform: UNKNOWN
Classifier: Development Status :: 3 - Alpha
Classifier: License :: OSI Approved :: MIT License
Classifier: Operating System :: OS Independent
Classifier: Programming Language :: Python
Classifier: Topic :: Software Development :: Libraries :: Python Modules
Requires-Dist: django
